jolly_brancher/__init__.py
jolly_brancher/config.py
jolly_brancher/forge.py
jolly_brancher/git.py
jolly_brancher/gitlab.py
jolly_brancher/input.py
jolly_brancher/issues.py
jolly_brancher/log.py
jolly_brancher/main.py
jolly_brancher/reviewers.py
jolly_brancher/user_input.py
jolly_brancher-1.1.1.dist-info/licenses/AUTHORS.rst
jolly_brancher-1.1.1.dist-info/licenses/LICENSE.txt
jolly_brancher-1.1.1.dist-info/METADATA
jolly_brancher-1.1.1.dist-info/WHEEL
jolly_brancher-1.1.1.dist-info/entry_points.txt
jolly_brancher-1.1.1.dist-info/top_level.txt
jolly_brancher-1.1.1.dist-info/RECORD
