Metadata-Version: 2.4
Name: jolly-brancher
Version: 1.1.1
Summary: CLI tool that creates git branches from JIRA tickets
Home-page: https://github.com/ahonnecke/jolly-brancher
Author: Ashton Von Honnecke
Author-email: ashton@pixelstub.com
License: MIT
Project-URL: Authentication, https://jira.readthedocs.io/en/latest/examples.html#username-api-token
Project-URL: Token, https://id.atlassian.com/manage-profile/security/api-tokens
Platform: Linux
Platform: Mac
Classifier: Development Status :: 4 - Beta
Classifier: Programming Language :: Python
License-File: LICENSE.txt
License-File: AUTHORS.rst
Requires-Dist: importlib-metadata; python_version > "3.10"
Requires-Dist: PyGithub
Requires-Dist: python-gitlab>=3.0.0
Requires-Dist: argparse
Requires-Dist: jira>=3.5.0
Requires-Dist: prompt_toolkit
Requires-Dist: requests
Provides-Extra: testing
Requires-Dist: setuptools; extra == "testing"
Requires-Dist: pytest; extra == "testing"
Requires-Dist: pytest-cov; extra == "testing"
Dynamic: license-file
